{
    "game_version": "0.98.2",
    "database_version": 1,
    "card": {
        "key": "Distraction",
        "category": "Event",
        "name_chs": "声东击西",
        "name_eng": "Distraction",
        "cost": 1,
        "rarity": "Event",
        "type": "Skill",
        "targetType": "Self",
        "text_raw_chs": "将一张随机技能牌添加到你的[gold]手牌[\/gold]中。这张牌在本回合内可以免费打出。",
        "text_default_chs": "消耗,将一张随机技能牌添加到你的手牌中。这张牌在本回合内可以免费打出。",
        "text_upgraded_chs": "消耗,将一张随机技能牌添加到你的手牌中。这张牌在本回合内可以免费打出。",
        "text_raw_eng": "Add a random Skill into your [gold]Hand[\/gold]. It's free to play this turn.",
        "variables": {
            "keywords": [
                "Exhaust"
            ]
        },
        "upgrades": {
            "costChange": -1
        }
    }
}