{
    "game_version": "0.98.2",
    "database_version": 1,
    "card": {
        "key": "Panache",
        "category": "Colorless",
        "name_chs": "神气制胜",
        "name_eng": "Panache",
        "cost": 0,
        "rarity": "Uncommon",
        "type": "Power",
        "targetType": "Self",
        "text_raw_chs": "每当你在一回合内打出五张牌时，对所有敌人造成{PanacheDamage:diff()}点伤害。",
        "text_default_chs": "每当你在一回合内打出五张牌时，对所有敌人造成10点伤害。",
        "text_upgraded_chs": "每当你在一回合内打出五张牌时，对所有敌人造成18点伤害。",
        "text_raw_eng": "Every time you play 5 cards in a single turn, deal {PanacheDamage:diff()} damage to ALL enemies.",
        "variables": {
            "PanacheDamage": 10
        },
        "upgrades": {
            "varChange": {
                "PanacheDamage": 4
            }
        }
    }
}