{
    "game_version": "0.98.2",
    "database_version": 1,
    "card": {
        "key": "Regret",
        "category": "Curse",
        "name_chs": "悔恨",
        "name_eng": "Regret",
        "cost": -1,
        "rarity": "Curse",
        "type": "Curse",
        "targetType": "None",
        "text_raw_chs": "在你的回合结束时，如果这张牌在你的[gold]手牌[\/gold]中，失去相当于[gold]手牌[\/gold]数量的生命。",
        "text_default_chs": "不能被打出,在你的回合结束时，如果这张牌在你的手牌中，失去相当于手牌数量的生命。",
        "text_upgraded_chs": "不能被打出,在你的回合结束时，如果这张牌在你的手牌中，失去相当于手牌数量的生命。",
        "text_raw_eng": "At the end of your turn, if this is in your [gold]Hand[\/gold], lose 1 HP for each card in your [gold]Hand[\/gold].",
        "variables": {
            "keywords": [
                "Unplayable"
            ]
        },
        "upgrades": []
    }
}