{
    "game_version": "0.98.2",
    "database_version": 1,
    "card": {
        "key": "RipAndTear",
        "category": "Event",
        "name_chs": "狂乱撕扯",
        "name_eng": "Rip and Tear",
        "cost": 1,
        "rarity": "Uncommon",
        "type": "Attack",
        "targetType": "RandomEnemy",
        "text_raw_chs": "随机对敌人造成{Damage:diff()}点伤害两次。",
        "text_default_chs": "随机对敌人造成7点伤害两次。",
        "text_upgraded_chs": "随机对敌人造成11点伤害两次。",
        "text_raw_eng": "Deal {Damage:diff()} damage to a random enemy twice.",
        "variables": {
            "Damage": "7m"
        },
        "upgrades": {
            "varChange": {
                "Damage": 2
            }
        }
    }
}