{
    "game_version": "0.98.2",
    "database_version": 1,
    "card": {
        "key": "Soot",
        "category": "Status",
        "name_chs": "煤灰",
        "name_eng": "Soot",
        "cost": -1,
        "rarity": "Status",
        "type": "Status",
        "targetType": "None",
        "text_raw_chs": "",
        "text_default_chs": "不能被打出",
        "text_upgraded_chs": "不能被打出",
        "text_raw_eng": "",
        "variables": {
            "keywords": [
                "Unplayable"
            ]
        },
        "upgrades": []
    }
}